pydtoc/__init__.py
python_dtoc-2023.10.5.dist-info/LICENSE
python_dtoc-2023.10.5.dist-info/METADATA
python_dtoc-2023.10.5.dist-info/WHEEL
python_dtoc-2023.10.5.dist-info/top_level.txt
python_dtoc-2023.10.5.dist-info/RECORD
