Metadata-Version: 2.1
Name: python-dtoc
Version: 2023.10.5
Summary: Awesome module for conver dict to class
Author: ZAID
Author-email: y8838@hotmail.com
Keywords: json
Classifier: Development Status :: 1 - Planning
Classifier: Intended Audience :: Developers
Classifier: Programming Language :: Python :: 3
Classifier: Operating System :: Unix
Classifier: Operating System :: MacOS :: MacOS X
Classifier: Operating System :: Microsoft :: Windows
Requires-Python: ~=3.6
License-File: LICENSE
